pygauth/__init__.py
pygauth-1.0.0.dist-info/LICENSE
pygauth-1.0.0.dist-info/METADATA
pygauth-1.0.0.dist-info/WHEEL
pygauth-1.0.0.dist-info/top_level.txt
pygauth-1.0.0.dist-info/RECORD
