Metadata-Version: 2.1
Name: pygauth
Version: 1.0.0
Summary: A Python helper library for Google Authentication
Home-page: https://git.squi.live/squili/pygauth
Author: Squili
License: UNKNOWN
Platform: UNKNOWN
Classifier: Programming Language :: Python :: 3
Classifier: License :: OSI Approved :: MIT License
Classifier: Operating System :: OS Independent
Requires-Python: >=3.5
Requires-Dist: bson
Requires-Dist: google-auth
Requires-Dist: google-auth-oauthlib
